glu_keras/__init__.py
glu_keras/glu.py
glu_keras/version.py
glu_keras-0.0.2.dist-info/LICENSE
glu_keras-0.0.2.dist-info/METADATA
glu_keras-0.0.2.dist-info/WHEEL
glu_keras-0.0.2.dist-info/RECORD
