Metadata-Version: 2.1
Name: GLU-KERAS
Version: 0.0.2
Summary: 
License: MIT
Author: Muhammad Anas Raza
Requires-Python: >=3.10,<4.0
Classifier: License :: OSI Approved :: MIT License
Classifier: Programming Language :: Python :: 3
Classifier: Programming Language :: Python :: 3.10
Classifier: Programming Language :: Python :: 3.11
Classifier: Programming Language :: Python :: 3.12
Requires-Dist: keras (>=3.0.0)
